paddle2onnx/__init__.py
paddle2onnx/command.py
paddle2onnx/convert.py
paddle2onnx/convert_to_fp16.py
paddle2onnx/optimize.py
paddle2onnx/paddle2onnx_cpp2py_export.cpython-38-x86_64-linux-gnu.so
paddle2onnx/utils.py
paddle2onnx/version.py
paddle2onnx/proto/CMakeLists.txt
paddle2onnx/proto/p2o_paddle.proto
paddle2onnx-2.0.1.dist-info/LICENSE
paddle2onnx-2.0.1.dist-info/METADATA
paddle2onnx-2.0.1.dist-info/WHEEL
paddle2onnx-2.0.1.dist-info/entry_points.txt
paddle2onnx-2.0.1.dist-info/top_level.txt
paddle2onnx-2.0.1.dist-info/RECORD
