Metadata-Version: 2.4
Name: paddle2onnx
Version: 2.0.1
Summary: Export PaddlePaddle to ONNX
Author-email: paddle-infer <paddle-infer@baidu.com>
License: Apache License v2.0
Classifier: Programming Language :: Python :: 3
Classifier: License :: OSI Approved :: Apache Software License
Classifier: Operating System :: OS Independent
Requires-Python: >=3.8
License-File: LICENSE
Requires-Dist: onnx>=1.16
Requires-Dist: onnxoptimizer==0.3.13
Requires-Dist: polygraphy>=0.49.20
Dynamic: license-file
